fastapi_migrate/__init__.py
fastapi_migrate/cli.py
fastapi_migrate/command.py
fastapi_migrate/templates/fastapi/README
fastapi_migrate/templates/fastapi/alembic.ini.mako
fastapi_migrate/templates/fastapi/env.py
fastapi_migrate/templates/fastapi/script.py.mako
fastapi_migrate-0.1.1.dist-info/WHEEL
fastapi_migrate-0.1.1.dist-info/METADATA
fastapi_migrate-0.1.1.dist-info/RECORD
