Metadata-Version: 2.1
Name: fastapi-migrate
Version: 0.1.1
Summary: 
Author: pengyj
Author-email: p15281826276@gmail.com
Requires-Python: >=3.6,<4.0
Classifier: Programming Language :: Python :: 3
Classifier: Programming Language :: Python :: 3.6
Classifier: Programming Language :: Python :: 3.7
Classifier: Programming Language :: Python :: 3.8
Requires-Dist: alembic (>=1.4.2,<2.0.0)
Requires-Dist: click (>=7.1.2,<8.0.0)
